rayse/__init__.py
rayse/antiplane_shear/__init__.py
rayse/consts/__init__.py
rayse/consts/ops.py
rayse/elasticity/__init__.py
rayse/plane_strain/__init__.py
rayse/plot/__init__.py
rayse/plot/plot.py
rayse/relaxed_antiplane_shear/__init__.py
rayse/relaxed_antiplane_shear_NII/__init__.py
rayse/relaxed_elasticity/__init__.py
rayse/relaxed_elasticity_NII/__init__.py
rayse/relaxed_plane_strain/__init__.py
rayse/relaxed_plane_strain_NII/__init__.py
rayse-0.1.1.data/data/README/README.md
rayse-0.1.1.data/data/licenses/APACHE2
rayse-0.1.1.data/data/licenses/MIT
rayse-0.1.1.dist-info/LICENSE
rayse-0.1.1.dist-info/METADATA
rayse-0.1.1.dist-info/WHEEL
rayse-0.1.1.dist-info/top_level.txt
rayse-0.1.1.dist-info/RECORD
