Metadata-Version: 2.1
Name: rayse
Version: 0.1.1
License: GNU LGPLv3
Classifier: License :: OSI Approved :: GNU Lesser General Public License v3 (LGPLv3)
Classifier: Intended Audience :: Science/Research
Classifier: Programming Language :: Rust
Classifier: Programming Language :: Python :: 3
Classifier: Development Status :: 3 - Alpha
Classifier: Operating System :: Microsoft :: Windows
Requires-Python: >=3.7
License-File: LICENSE
Requires-Dist: plana
Requires-Dist: replana
Requires-Dist: replanaii
Requires-Dist: pane
Requires-Dist: repane
Requires-Dist: repaneii
Requires-Dist: elast
Requires-Dist: relast
Requires-Dist: relastii
Requires-Dist: plotly
